GameTracker/GameTracker.py
GameTracker/__init__.py
GameTracker/countries.py
GameTracker-2.0.1.dist-info/LICENSE
GameTracker-2.0.1.dist-info/METADATA
GameTracker-2.0.1.dist-info/WHEEL
GameTracker-2.0.1.dist-info/top_level.txt
GameTracker-2.0.1.dist-info/RECORD
