Metadata-Version: 2.1
Name: GameTracker
Version: 2.0.1
Summary: A simple way to get player stats from a variety of games.
Home-page: https://github.com/harrykearney/GameTracker
Author: Harry Kearney
Author-email: kearneyharry8@gmail.com
License: UNKNOWN
Platform: UNKNOWN
Classifier: Programming Language :: Python :: 3
Classifier: Operating System :: OS Independent
Requires-Python: >=3.6
Requires-Dist: requests
